AUTHORS.rst
CONTRIBUTING.rst
HISTORY.rst
LICENSE
MANIFEST.in
README.rst
setup.cfg
setup.py
docs/Makefile
docs/authors.rst
docs/conf.py
docs/contributing.rst
docs/history.rst
docs/index.rst
docs/installation.rst
docs/make.bat
docs/readme.rst
docs/usage.rst
outlookmail/API.py
outlookmail/Mail.py
outlookmail/__init__.py
outlookmail/cli.py
outlookmail.egg-info/PKG-INFO
outlookmail.egg-info/SOURCES.txt
outlookmail.egg-info/dependency_links.txt
outlookmail.egg-info/entry_points.txt
outlookmail.egg-info/not-zip-safe
outlookmail.egg-info/requires.txt
outlookmail.egg-info/top_level.txt
tests/__init__.py
tests/test_outlookmail.py