Metadata-Version: 2.1
Name: outlookmail
Version: 0.0.3
Summary: Make automatic many email related tasks in Outlook
Home-page: https://github.com/luisggc/outlookmail
Author: Luis Gabriel Gonçalves Coimbra
Author-email: luiscoimbraeng@outlook.com
License: MIT license
Keywords: outlookmail
Platform: UNKNOWN
Classifier: Development Status :: 2 - Pre-Alpha
Classifier: Intended Audience :: Developers
Classifier: License :: OSI Approved :: MIT License
Classifier: Natural Language :: English
Classifier: Programming Language :: Python :: 3
Classifier: Programming Language :: Python :: 3.6
Classifier: Programming Language :: Python :: 3.7
Classifier: Programming Language :: Python :: 3.8
Requires-Python: >=3.6
License-File: LICENSE
License-File: AUTHORS.rst
